
{
  "1":{ "days":{"20170709":{"status":"free"},"20170710":{"status":"free"} } },
  "2":{ "days":{"20170710":{"status":"hold"},"20170711":{"status":"hold"} } },
  "3":{ "days":{"20170711":{"status":"free"},"20170712":{"status":"free"} } },
  "4":{ "days":{"20170715":{"status":"book"},"20170716":{"status":"book"} } },
  "5":{ "days":{"20170721":{"status":"hold"},"20170722":{"status":"hold"} } },
  "6":{ "days":{"20170714":{"status":"free"},"20170715":{"status":"free"} } },
  "7":{ "days":{"20170720":{"status":"book"},"20170722":{"status":"book"} } },
  "8":{ "days":{"20170719":{"status":"hold"},"20170720":{"status":"hold"} } },
  "N":{ "days":{"20170721":{"status":"free"},"20170722":{"status":"free"} } },
  "S":{ "days":{"20170724":{"status":"book"},"20170725":{"status":"book"} } }
}