{
  "1":{ "total":250, "paid":250, "balance":0,
    "rooms":  { "1":{ "total":250, "price":125, "guests":2,"pets":1, "spa":false, "days":{"20170709":{},"20170710":{} } } },
    "payments":{"1":{ "amount":250,"date":"20170517", "with":"check", "num":"4028" } }, 
    "status":"book", "method":"site", "custId":"1" },
  "2":{ "total":250, "paid":250, "balance":0,
    "rooms":  { "2":{ "total":250, "price":125, "guests":2,"pets":1, "spa":false, "days":{"20170710":{},"20170711":{} } } },
    "payments":{"2":{ "amount":250,"date":"20170517", "with":"check", "num":"4028" } },
    "status":"depo", "method":"booking", "custId":"2" },
  "3":{ "total":250, "paid":250, "balance":0,
    "rooms":  { "3":{ "total":250, "price":125, "guests":2,"pets":1, "spa":false, "days":{"20170711":{},"20170712":{} } } },
    "payments":{"3":{ "amount":250,"date":"20170517", "with":"check", "num":"4028" } },
    "status":"book", "method":"walkin", "custId":"3" },
  "4":{ "total":250, "paid":250, "balance":0,
    "rooms":  { "4":{ "total":250, "price":125, "guests":2,"pets":1, "spa":false, "days":{"20170712":{},"20170713":{} } } },
    "payments":{"4":{ "amount":250,"date":"20170517", "with":"check", "num":"4028" } },
    "status":"book", "method":"phone", "custId":"4" },
  "5":{ "total":250, "paid":250, "balance":0,
    "rooms":   { "5":{ "total":250, "price":125, "guests":2,"pets":1, "spa":false, "days":{"20170714":{},"20170715":{} } } },
    "payments":{ "1":{ "amount":250,"date":"20170517", "with":"check", "num":"4028" } },
    "status":"depo", "method":"email", "custId":"5"  },
  "6":{ "total":250, "paid":250, "balance":0,
    "rooms":  { "6":{ "total":250, "price":125, "guests":2,"pets":1, "spa":false, "days":{"20170715":{},"20170716":{} } } },
    "payments":{"1":{ "amount":250,"date":"20170517", "with":"check", "num":"4028" } },
    "status":"depo", "method":"site", "custId":"6"},
  "7":{ "total":250, "paid":250, "balance":0,
    "rooms":  { "7":{ "total":250, "price":125, "guests":2,"pets":1, "spa":false, "days":{"20170716":{},"20170717":{} } } },
    "payments":{"1":{ "amount":250,"date":"20170517", "with":"check", "num":"4028" } },
    "status":"book", "method":"booking", "custId":"7" },
  "8":{ "total":250, "paid":250, "balance":0,
    "rooms":  { "8":{ "total":250, "price":125, "guests":2,"pets":1, "spa":false, "days":{"20170717":{},"20170718":{} } } },
    "payments":{"1":{ "amount":250,"date":"20170517", "with":"check", "num":"4028" } },
    "status":"depo", "method":"walkin", "custId":"8" },
  "9":{ "total":250, "paid":250, "balance":0,
    "rooms":  { "N":{ "total":250, "price":125, "guests":2,"pets":1, "spa":false, "days":{"20170718":{},"20170719":{} } } },
    "payments":{"1":{ "amount":250,"date":"20170517", "with":"check", "num":"4028" } },
    "status":"depo", "method":"email", "custId":"9" },
  "10":{ "total":250, "paid":250, "balance":0,
    "rooms":  { "S":{ "total":250, "price":125, "guests":2,"pets":1, "spa":false, "days":{"20170719":{},"20170720":{} } } },
    "payments":{"10":{ "amount":250,"date":"20170517", "with":"check", "num":"4028" } },
    "status":"book", "method":"site",
    "custId":"10" }
}